ManongFanshenQuannianWenzhangJinghua2016/README.md
ManongFanshenQuannianWenzhangJinghua2016/__init__.py
ManongFanshenQuannianWenzhangJinghua2016/__main__.py
ManongFanshenQuannianWenzhangJinghua2016/file.epub
ManongFanshenQuannianWenzhangJinghua2016/index.html
ManongFanshenQuannianWenzhangJinghua2016/css/__init__.py
ManongFanshenQuannianWenzhangJinghua2016/css/annotations.css
ManongFanshenQuannianWenzhangJinghua2016/css/main.css
ManongFanshenQuannianWenzhangJinghua2016/css/normalize.css
ManongFanshenQuannianWenzhangJinghua2016/css/popup.css
ManongFanshenQuannianWenzhangJinghua2016/font/__init__.py
ManongFanshenQuannianWenzhangJinghua2016/font/fontello.eot
ManongFanshenQuannianWenzhangJinghua2016/font/fontello.svg
ManongFanshenQuannianWenzhangJinghua2016/font/fontello.ttf
ManongFanshenQuannianWenzhangJinghua2016/font/fontello.woff
ManongFanshenQuannianWenzhangJinghua2016/img/__init__.py
ManongFanshenQuannianWenzhangJinghua2016/img/annotator-glyph-sprite.png
ManongFanshenQuannianWenzhangJinghua2016/img/annotator-icon-sprite.png
ManongFanshenQuannianWenzhangJinghua2016/img/apple-touch-icon.png
ManongFanshenQuannianWenzhangJinghua2016/img/cancelfullscreen.png
ManongFanshenQuannianWenzhangJinghua2016/img/close.png
ManongFanshenQuannianWenzhangJinghua2016/img/fullscreen.png
ManongFanshenQuannianWenzhangJinghua2016/img/loader.gif
ManongFanshenQuannianWenzhangJinghua2016/img/menu-icon.png
ManongFanshenQuannianWenzhangJinghua2016/img/save.png
ManongFanshenQuannianWenzhangJinghua2016/img/saved.png
ManongFanshenQuannianWenzhangJinghua2016/img/settings-s.png
ManongFanshenQuannianWenzhangJinghua2016/img/settings.png
ManongFanshenQuannianWenzhangJinghua2016/img/star.png
ManongFanshenQuannianWenzhangJinghua2016/js/__init__.py
ManongFanshenQuannianWenzhangJinghua2016/js/epub.js
ManongFanshenQuannianWenzhangJinghua2016/js/epub.min.js
ManongFanshenQuannianWenzhangJinghua2016/js/epub.min.map
ManongFanshenQuannianWenzhangJinghua2016/js/hooks.min.js
manong_fanshen_quannian_wenzhang_jinghua_2016-2024.3.4.0.dist-info/METADATA
manong_fanshen_quannian_wenzhang_jinghua_2016-2024.3.4.0.dist-info/WHEEL
manong_fanshen_quannian_wenzhang_jinghua_2016-2024.3.4.0.dist-info/entry_points.txt
manong_fanshen_quannian_wenzhang_jinghua_2016-2024.3.4.0.dist-info/top_level.txt
manong_fanshen_quannian_wenzhang_jinghua_2016-2024.3.4.0.dist-info/RECORD
